{
  "content": [
    {
      "memberId": 7,
      "fullName": "Vada Shaeffer",
      "emailAddress": "VadaShaeffer8856@gmail.com",
      "isActive": false
    },
    {
      "memberId": 10,
      "fullName": "Joella Verne",
      "emailAddress": "JoellaVerne6703@gmail.com",
      "isActive": false
    },
    {
      "memberId": 12,
      "fullName": "Bettyann Kizer",
      "emailAddress": "BettyannKizer7813@gmail.com",
      "isActive": false
    },
    {
      "memberId": 32,
      "fullName": "Fleta Giampaolo",
      "emailAddress": "FletaGiampaolo3754@gmail.com",
      "isActive": true
    },
    {
      "memberId": 35,
      "fullName": "Sarai Morelli",
      "emailAddress": "SaraiMorelli9034@gmail.com",
      "isActive": true
    },
    {
      "memberId": 36,
      "fullName": "Lashanda Abbott",
      "emailAddress": "LashandaAbbott9174@gmail.com",
      "isActive": true
    },
    {
      "memberId": 104,
      "fullName": "Leila Odle",
      "emailAddress": "LeilaOdle4383@gmail.com",
      "isActive": true
    },
    {
      "memberId": 107,
      "fullName": "Abby Peevy",
      "emailAddress": "AbbyPeevy0877@gmail.com",
      "isActive": true
    },
    {
      "memberId": 131,
      "fullName": "Stacie Austria",
      "emailAddress": "StacieAustria9018@gmail.com",
      "isActive": true
    },
    {
      "memberId": 146,
      "fullName": "Elvis Leatherwood",
      "emailAddress": "ElvisLeatherwood1278@gmail.com",
      "isActive": true
    }
  ],
  "pageNumber": 1,
  "pageSize": 10,
  "totalElements": 14,
  "numberOfElements": 10
}